pytest_tblineinfo.py
pytest_tblineinfo-0.4.dist-info/DESCRIPTION.rst
pytest_tblineinfo-0.4.dist-info/METADATA
pytest_tblineinfo-0.4.dist-info/RECORD
pytest_tblineinfo-0.4.dist-info/WHEEL
pytest_tblineinfo-0.4.dist-info/entry_points.txt
pytest_tblineinfo-0.4.dist-info/metadata.json
pytest_tblineinfo-0.4.dist-info/top_level.txt
