Metadata-Version: 2.0
Name: pytest-tblineinfo
Version: 0.4
Summary: tblineinfo is a py.test plugin that insert the node id in the final py.test report when --tb=line option is used
Home-page: https://github.com/matclab/pytest-tblineinfo
Author: Mathieu Clabaut
Author-email: mathieu.clabaut@systerel.fr, mathieu@clabaut.net
License: MIT
Platform: any
Classifier: Development Status :: 3 - Alpha
Classifier: Intended Audience :: Developers
Classifier: License :: OSI Approved :: MIT License
Classifier: Operating System :: POSIX
Classifier: Operating System :: Microsoft :: Windows
Classifier: Operating System :: MacOS :: MacOS X
Classifier: Topic :: Software Development :: Testing
Classifier: Topic :: Software Development :: Libraries
Classifier: Topic :: Utilities
Classifier: Programming Language :: Python :: 2
Classifier: Programming Language :: Python :: 2.7
Classifier: Programming Language :: Python :: 3
Classifier: Programming Language :: Python :: 3.4
Classifier: Programming Language :: Python :: Implementation :: PyPy
Requires-Dist: pytest (>=2.0)
